st_wordcloud/__init__.py
st_wordcloud/frontend/build/asset-manifest.json
st_wordcloud/frontend/build/index.html
st_wordcloud/frontend/build/static/js/main.c5e34a2c.js
st_wordcloud/frontend/build/static/js/main.c5e34a2c.js.LICENSE.txt
st_wordcloud/frontend/build/static/js/main.c5e34a2c.js.map
st_wordcloud-0.0.7.dist-info/LICENSE
st_wordcloud-0.0.7.dist-info/METADATA
st_wordcloud-0.0.7.dist-info/WHEEL
st_wordcloud-0.0.7.dist-info/top_level.txt
st_wordcloud-0.0.7.dist-info/RECORD
