Metadata-Version: 2.1
Name: st-wordcloud
Version: 0.0.7
Summary: st_wordcloud React component for Streamlit
Home-page: https://github.com/drogbadvc/st-wordcloud
Author: Andell
Author-email: drogadvc@gmail.com
Requires-Python: >=3.7
License-File: LICENSE
Requires-Dist: streamlit >=0.63
